{
    "10c.sql": {
        "speedup": 9.601824224902833,
        "speedupAbs": 6.626905679702759,
        "opt": 62
    },
    "22d.sql": {
        "speedup": 1.0531916093673348,
        "speedupAbs": 157.62786388397217,
        "opt": 43
    },
    "11a.sql": {
        "speedup": 2.4807537347745106,
        "speedupAbs": 0.305941104888916,
        "opt": 47
    },
    "14b.sql": {
        "speedup": 1.1251796923021793,
        "speedupAbs": 41.67561483383179,
        "opt": 47
    },
    "15c.sql": {
        "speedup": 3.601367171583815,
        "speedupAbs": 20.828123331069946,
        "opt": 62
    },
    "11c.sql": {
        "speedup": 1.1156975727376743,
        "speedupAbs": 4.044731378555298,
        "opt": 43
    },
    "31b.sql": {
        "speedup": 4.288053176717483,
        "speedupAbs": 24.382606744766235,
        "opt": 62
    },
    "7c.sql": {
        "speedup": 24.615871889935192,
        "speedupAbs": 6.468828201293945,
        "opt": 62
    },
    "24b.sql": {
        "speedup": 79.11859916482575,
        "speedupAbs": 0.9556450843811035,
        "opt": 62
    },
    "17b.sql": {
        "speedup": 1.3037079403350624,
        "speedupAbs": 143.2966170310974,
        "opt": 39
    },
    "22a.sql": {
        "speedup": 1.22583299238661,
        "speedupAbs": 62.472864627838135,
        "opt": 59
    },
    "13d.sql": {
        "speedup": 1.1796670616041187,
        "speedupAbs": 89.50685048103333,
        "opt": 51
    },
    "8c.sql": {
        "speedup": 0,
        "speedupAbs": 0.0,
        "opt": 63
    },
    "16b.sql": {
        "speedup": 3.8340906508620525,
        "speedupAbs": 29.973156929016113,
        "opt": 51
    },
    "17e.sql": {
        "speedup": 1.56272967108887,
        "speedupAbs": 115.01433372497559,
        "opt": 54
    },
    "16d.sql": {
        "speedup": 1.584404243711727,
        "speedupAbs": 95.88900542259216,
        "opt": 39
    },
    "9c.sql": {
        "speedup": 6.471463087670896,
        "speedupAbs": 15.116124391555786,
        "opt": 62
    },
    "8d.sql": {
        "speedup": 95.22182877546658,
        "speedupAbs": 0.579176664352417,
        "opt": 39
    },
    "2a.sql": {
        "speedup": 1.0856084053849864,
        "speedupAbs": 12.003628492355347,
        "opt": 47
    },
    "23b.sql": {
        "speedup": 1.134055990526163,
        "speedupAbs": 19.403589725494385,
        "opt": 43
    },
    "2b.sql": {
        "speedup": 1.0255746539673334,
        "speedupAbs": 39.347288846969604,
        "opt": 47
    },
    "19c.sql": {
        "speedup": 33.617804358909304,
        "speedupAbs": 2.9335339069366455,
        "opt": 62
    },
    "32a.sql": {
        "speedup": 1.2056271326571686,
        "speedupAbs": 0.19724678993225098,
        "opt": 42
    },
    "2d.sql": {
        "speedup": 1.0333548806300805,
        "speedupAbs": 36.89515519142151,
        "opt": 47
    },
    "15b.sql": {
        "speedup": 1.1416050722110322,
        "speedupAbs": 33.27019166946411,
        "opt": 58
    },
    "23c.sql": {
        "speedup": 7.816629040001779,
        "speedupAbs": 4.823393106460571,
        "opt": 62
    },
    "9d.sql": {
        "speedup": 1.3447103864133088,
        "speedupAbs": 220.68256998062134,
        "opt": 55
    },
    "11b.sql": {
        "speedup": 5.9352080614674945,
        "speedupAbs": 5.565297365188599,
        "opt": 62
    },
    "1a.sql": {
        "speedup": 1.0371116661603883,
        "speedupAbs": 4.229680776596069,
        "opt": 47
    },
    "12c.sql": {
        "speedup": 1.0474056011429318,
        "speedupAbs": 75.35294008255005,
        "opt": 46
    },
    "33c.sql": {
        "speedup": 1.1740361556184955,
        "speedupAbs": 2.6448018550872803,
        "opt": 42
    },
    "5c.sql": {
        "speedup": 1.1173923122646292,
        "speedupAbs": 24.653224229812622,
        "opt": 58
    },
    "10a.sql": {
        "speedup": 5.307085873068023,
        "speedupAbs": 25.34897541999817,
        "opt": 62
    },
    "25a.sql": {
        "speedup": 20.546311584801973,
        "speedupAbs": 5.170919179916382,
        "opt": 62
    },
    "30c.sql": {
        "speedup": 4.7158832157554444,
        "speedupAbs": 19.514188289642334,
        "opt": 62
    },
    "19b.sql": {
        "speedup": 3.567264278043625,
        "speedupAbs": 15.750965595245361,
        "opt": 48
    },
    "8b.sql": {
        "speedup": 1.8318278059126807,
        "speedupAbs": 38.45819854736328,
        "opt": 42
    },
    "18a.sql": {
        "speedup": 8.347701082388436,
        "speedupAbs": 18.32430672645569,
        "opt": 62
    },
    "14c.sql": {
        "speedup": 1.0465243021824526,
        "speedupAbs": 118.6882963180542,
        "opt": 58
    },
    "27c.sql": {
        "speedup": 1.0398492891196653,
        "speedupAbs": 25.292755603790283,
        "opt": 24
    },
    "29c.sql": {
        "speedup": 14.700065349166398,
        "speedupAbs": 6.693682432174683,
        "opt": 39
    },
    "31c.sql": {
        "speedup": 1.531709767141824,
        "speedupAbs": 97.56161403656006,
        "opt": 39
    },
    "18c.sql": {
        "speedup": 6.130421313818107,
        "speedupAbs": 29.895622730255127,
        "opt": 62
    },
    "25b.sql": {
        "speedup": 3.0341572945858672,
        "speedupAbs": 19.455080032348633,
        "opt": 59
    },
    "21c.sql": {
        "speedup": 1.3076174253917574,
        "speedupAbs": 4.591199636459351,
        "opt": 47
    },
    "17c.sql": {
        "speedup": 1.3466229691269778,
        "speedupAbs": 147.36727333068848,
        "opt": 35
    },
    "27b.sql": {
        "speedup": 1.3915172485909877,
        "speedupAbs": 2.9206864833831787,
        "opt": 56
    },
    "17a.sql": {
        "speedup": 4.878148558185347,
        "speedupAbs": 36.555060386657715,
        "opt": 62
    },
    "10b.sql": {
        "speedup": 24.75628117743011,
        "speedupAbs": 1.455826759338379,
        "opt": 51
    },
    "6d.sql": {
        "speedup": 1.3750275153289775,
        "speedupAbs": 114.72159337997437,
        "opt": 50
    },
    "17f.sql": {
        "speedup": 1.345263120008598,
        "speedupAbs": 164.74488139152527,
        "opt": 51
    },
    "13b.sql": {
        "speedup": 1.044987943224291,
        "speedupAbs": 115.2715060710907,
        "opt": 38
    },
    "24a.sql": {
        "speedup": 59.144895565914354,
        "speedupAbs": 1.1318104267120361,
        "opt": 47
    },
    "20c.sql": {
        "speedup": 14.631759484795134,
        "speedupAbs": 7.642687082290649,
        "opt": 62
    },
    "28b.sql": {
        "speedup": 7.708006399257895,
        "speedupAbs": 3.585933208465576,
        "opt": 62
    },
    "25c.sql": {
        "speedup": 6.7415442803855035,
        "speedupAbs": 19.14572286605835,
        "opt": 62
    },
    "28c.sql": {
        "speedup": 1.0760362850314849,
        "speedupAbs": 243.1574079990387,
        "opt": 50
    },
    "23a.sql": {
        "speedup": 1.0437208718697863,
        "speedupAbs": 57.7692129611969,
        "opt": 42
    },
    "14a.sql": {
        "speedup": 1.087288672912799,
        "speedupAbs": 134.4380238056183,
        "opt": 42
    },
    "2c.sql": {
        "speedup": 1.0470801502030012,
        "speedupAbs": 18.774881601333618,
        "opt": 34
    },
    "11d.sql": {
        "speedup": 8.8359924770786,
        "speedupAbs": 0.06084918975830078,
        "opt": 62
    },
    "26a.sql": {
        "speedup": 1.6267129322847333,
        "speedupAbs": 95.07675075531006,
        "opt": 51
    },
    "1c.sql": {
        "speedup": 1.0350942534348522,
        "speedupAbs": 4.265273094177246,
        "opt": 58
    },
    "7b.sql": {
        "speedup": 10.072076036200341,
        "speedupAbs": 7.274174451828003,
        "opt": 55
    },
    "7a.sql": {
        "speedup": 3.7943821010855823,
        "speedupAbs": 13.831556558609009,
        "opt": 62
    },
    "30b.sql": {
        "speedup": 14.953490242575063,
        "speedupAbs": 5.101512670516968,
        "opt": 62
    },
    "3a.sql": {
        "speedup": 7.474345834362378,
        "speedupAbs": 6.237285852432251,
        "opt": 62
    },
    "6b.sql": {
        "speedup": 1.3474121666337993,
        "speedupAbs": 124.68045616149902,
        "opt": 39
    },
    "1d.sql": {
        "speedup": 1.1313262545431013,
        "speedupAbs": 1.1199729442596436,
        "opt": 46
    },
    "17d.sql": {
        "speedup": 1.356687882028703,
        "speedupAbs": 148.92334175109863,
        "opt": 50
    },
    "32b.sql": {
        "speedup": 13.303443244279286,
        "speedupAbs": 0.038561105728149414,
        "opt": 62
    },
    "4c.sql": {
        "speedup": 1.0383851007947473,
        "speedupAbs": 24.133983850479126,
        "opt": 47
    },
    "29a.sql": {
        "speedup": 4.616680564218335,
        "speedupAbs": 14.636447429656982,
        "opt": 62
    },
    "15a.sql": {
        "speedup": 1.294382469927176,
        "speedupAbs": 9.135977029800415,
        "opt": 43
    },
    "31a.sql": {
        "speedup": 4.772143532652865,
        "speedupAbs": 26.17473006248474,
        "opt": 62
    },
    "20a.sql": {
        "speedup": 5.638823973793884,
        "speedupAbs": 30.61176872253418,
        "opt": 62
    },
    "26b.sql": {
        "speedup": 3.9017305977611296,
        "speedupAbs": 17.228912591934204,
        "opt": 49
    },
    "28a.sql": {
        "speedup": 1.0747210589301077,
        "speedupAbs": 279.1421992778778,
        "opt": 54
    },
    "33a.sql": {
        "speedup": 3.187117189671515,
        "speedupAbs": 0.16726374626159668,
        "opt": 62
    },
    "33b.sql": {
        "speedup": 1.0798517078188763,
        "speedupAbs": 3.0185415744781494,
        "opt": 47
    },
    "16c.sql": {
        "speedup": 1.8034235514298953,
        "speedupAbs": 70.05339479446411,
        "opt": 51
    },
    "19a.sql": {
        "speedup": 1.421009654287373,
        "speedupAbs": 120.06119728088379,
        "opt": 49
    },
    "6e.sql": {
        "speedup": 1.9499793642572223,
        "speedupAbs": 41.94040274620056,
        "opt": 44
    },
    "18b.sql": {
        "speedup": 4.195951770345667,
        "speedupAbs": 16.689637660980225,
        "opt": 62
    },
    "4b.sql": {
        "speedup": 1.1075438238239927,
        "speedupAbs": 6.843041658401489,
        "opt": 58
    },
    "22b.sql": {
        "speedup": 4.169244451548457,
        "speedupAbs": 12.469817399978638,
        "opt": 62
    },
    "13c.sql": {
        "speedup": 1.0557493930701989,
        "speedupAbs": 110.24766182899475,
        "opt": 54
    },
    "29b.sql": {
        "speedup": 29.307473421425158,
        "speedupAbs": 3.317474603652954,
        "opt": 62
    },
    "6c.sql": {
        "speedup": 3.6662479836420347,
        "speedupAbs": 13.706634521484375,
        "opt": 62
    },
    "26c.sql": {
        "speedup": 1.3601923915097134,
        "speedupAbs": 170.6705243587494,
        "opt": 55
    },
    "3b.sql": {
        "speedup": 2.524062182911115,
        "speedupAbs": 1.2761123180389404,
        "opt": 58
    },
    "27a.sql": {
        "speedup": 1.0320158428998591,
        "speedupAbs": 32.28343105316162,
        "opt": 25
    },
    "12a.sql": {
        "speedup": 1.0574771394276383,
        "speedupAbs": 44.73104476928711,
        "opt": 43
    },
    "12b.sql": {
        "speedup": 1.1042815421532897,
        "speedupAbs": 18.866422414779663,
        "opt": 47
    },
    "6f.sql": {
        "speedup": 1.4329656121078789,
        "speedupAbs": 125.88640999794006,
        "opt": 39
    },
    "21b.sql": {
        "speedup": 1.0969316443583095,
        "speedupAbs": 5.919756889343262,
        "opt": 43
    },
    "21a.sql": {
        "speedup": 1.0584158772800898,
        "speedupAbs": 24.018497943878174,
        "opt": 46
    },
    "30a.sql": {
        "speedup": 1.4241828013768245,
        "speedupAbs": 130.59898567199707,
        "opt": 41
    },
    "19d.sql": {
        "speedup": 13.71485444804919,
        "speedupAbs": 13.675091981887817,
        "opt": 55
    },
    "1b.sql": {
        "speedup": 5.386109673907932,
        "speedupAbs": 0.035482168197631836,
        "opt": 62
    },
    "9a.sql": {
        "speedup": 492.5164274352447,
        "speedupAbs": 0.1007232666015625,
        "opt": 62
    },
    "9b.sql": {
        "speedup": 11.347269960392527,
        "speedupAbs": 3.249344825744629,
        "opt": 49
    },
    "5a.sql": {
        "speedup": 1.285669659451521,
        "speedupAbs": 3.0460236072540283,
        "opt": 47
    },
    "5b.sql": {
        "speedup": 1.0994309400672497,
        "speedupAbs": 4.314879894256592,
        "opt": 42
    },
    "22c.sql": {
        "speedup": 4.1041763874410915,
        "speedupAbs": 26.989596366882324,
        "opt": 62
    },
    "13a.sql": {
        "speedup": 1.051716402867934,
        "speedupAbs": 109.73871850967407,
        "opt": 35
    },
    "4a.sql": {
        "speedup": 1.0307048455892276,
        "speedupAbs": 30.706448554992676,
        "opt": 42
    },
    "6a.sql": {
        "speedup": 2.5774142265724933,
        "speedupAbs": 21.921888828277588,
        "opt": 46
    },
    "15d.sql": {
        "speedup": 1.1802850500862225,
        "speedupAbs": 55.817599058151245,
        "opt": 60
    },
    "20b.sql": {
        "speedup": 2.2543863654461997,
        "speedupAbs": 45.72996664047241,
        "opt": 39
    },
    "3c.sql": {
        "speedup": 1.140147999465948,
        "speedupAbs": 21.06986689567566,
        "opt": 47
    },
    "16a.sql": {
        "speedup": 7.864705912770348,
        "speedupAbs": 5.809510231018066,
        "opt": 62
    },
    "8a.sql": {
        "speedup": 6.080803258675823,
        "speedupAbs": 6.559380054473877,
        "opt": 62
    },
    "avrgTOT": {
        "speedup": 10.670451644559538,
        "speedupAbs": 4899.39977145195,
        "speedupAvg": 43.35752010134469,
        "pg_def": 9404.162893533707,
        "runtime": 107984.84648489952,
        "factor": 0.045371178743464496
    },
    "62": {
        "total_speedup": 877.9412414231891,
        "count": 36,
        "average_speedup": 24.387256706199697
    },
    "43": {
        "total_speedup": 6.751736426344295,
        "count": 6,
        "average_speedup": 1.1252894043907158
    },
    "47": {
        "total_speedup": 73.88843203420996,
        "count": 13,
        "average_speedup": 5.683725541093073
    },
    "39": {
        "total_speedup": 119.37648022000946,
        "count": 8,
        "average_speedup": 14.922060027501182
    },
    "59": {
        "total_speedup": 4.259990286972477,
        "count": 2,
        "average_speedup": 2.1299951434862385
    },
    "51": {
        "total_speedup": 34.545438493619514,
        "count": 6,
        "average_speedup": 5.757573082269919
    },
    "63": {
        "total_speedup": 0,
        "count": 1,
        "average_speedup": 0.0
    },
    "54": {
        "total_speedup": 3.693200123089177,
        "count": 3,
        "average_speedup": 1.2310667076963924
    },
    "42": {
        "total_speedup": 8.472636424627408,
        "count": 7,
        "average_speedup": 1.2103766320896299
    },
    "58": {
        "total_speedup": 7.972221946828075,
        "count": 6,
        "average_speedup": 1.3287036578046791
    },
    "55": {
        "total_speedup": 26.491833262172555,
        "count": 4,
        "average_speedup": 6.622958315543139
    },
    "46": {
        "total_speedup": 5.814561959538616,
        "count": 4,
        "average_speedup": 1.453640489884654
    },
    "48": {
        "total_speedup": 3.567264278043625,
        "count": 1,
        "average_speedup": 3.567264278043625
    },
    "24": {
        "total_speedup": 1.0398492891196653,
        "count": 1,
        "average_speedup": 1.0398492891196653
    },
    "35": {
        "total_speedup": 2.3983393719949118,
        "count": 2,
        "average_speedup": 1.1991696859974559
    },
    "56": {
        "total_speedup": 1.3915172485909877,
        "count": 1,
        "average_speedup": 1.3915172485909877
    },
    "50": {
        "total_speedup": 3.8077516823891653,
        "count": 3,
        "average_speedup": 1.2692505607963884
    },
    "38": {
        "total_speedup": 1.044987943224291,
        "count": 1,
        "average_speedup": 1.044987943224291
    },
    "34": {
        "total_speedup": 1.0470801502030012,
        "count": 1,
        "average_speedup": 1.0470801502030012
    },
    "49": {
        "total_speedup": 16.670010212441028,
        "count": 3,
        "average_speedup": 5.556670070813676
    },
    "44": {
        "total_speedup": 1.9499793642572223,
        "count": 1,
        "average_speedup": 1.9499793642572223
    },
    "25": {
        "total_speedup": 1.0320158428998591,
        "count": 1,
        "average_speedup": 1.0320158428998591
    },
    "41": {
        "total_speedup": 1.4241828013768245,
        "count": 1,
        "average_speedup": 1.4241828013768245
    },
    "60": {
        "total_speedup": 1.1802850500862225,
        "count": 1,
        "average_speedup": 1.1802850500862225
    }
}